llmengine/__init__.py
llmengine/api_engine.py
llmengine/completion.py
llmengine/data_types/__init__.py
llmengine/data_types/batch_completion.py
llmengine/data_types/chat_completion.py
llmengine/data_types/completion.py
llmengine/data_types/core.py
llmengine/data_types/gen/__init__.py
llmengine/data_types/gen/openai.py
llmengine/data_types/model_endpoints.py
llmengine/data_types/pydantic_types.py
llmengine/data_types/rest.py
llmengine/data_types/vllm.py
llmengine/errors.py
llmengine/file.py
llmengine/fine_tuning.py
llmengine/model.py
llmengine/py.typed
scale_llm_engine-0.0.0b45.dist-info/METADATA
scale_llm_engine-0.0.0b45.dist-info/WHEEL
scale_llm_engine-0.0.0b45.dist-info/RECORD
