Metadata-Version: 2.3
Name: scale-llm-engine
Version: 0.0.0b45
Summary: Scale LLM Engine Python client
License: Apache-2.0
Author: Phil Chen
Author-email: phil.chen@scale.com
Maintainer: Phil Chen
Maintainer-email: phil.chen@scale.com
Requires-Python: >=3.8,<4.0
Classifier: License :: OSI Approved :: Apache Software License
Classifier: Programming Language :: Python :: 3
Classifier: Programming Language :: Python :: 3.8
Classifier: Programming Language :: Python :: 3.9
Classifier: Programming Language :: Python :: 3.10
Classifier: Programming Language :: Python :: 3.11
Classifier: Programming Language :: Python :: 3.12
Classifier: Programming Language :: Python :: 3.13
Requires-Dist: aiohttp (>=3.8,<4.0)
Requires-Dist: openai (>=1.30.0,<2.0.0)
Requires-Dist: pydantic (>=1.10.17)
Requires-Dist: requests (>=2.31.0,<3.0.0)
Project-URL: Homepage, https://scaleapi.github.io/llm-engine/
Project-URL: Repository, https://github.com/scaleapi/llm-engine
